dlxapi/__init__.py
dlxapi/access_token.py
dlxapi/api_client.py
dlxapi/configuration.py
dlxapi/constants.py
dlxapi/from_json.py
dlxapi/quick_start_example.py
dlxapi/rest.py
dlxapi/api/__init__.py
dlxapi/api/activities_api.py
dlxapi/api/api_activity_api.py
dlxapi/api/attachments_api.py
dlxapi/api/classification_api.py
dlxapi/api/comments_api.py
dlxapi/api/default_api.py
dlxapi/api/fields_api.py
dlxapi/api/groups_api.py
dlxapi/api/logout_api.py
dlxapi/api/mail_api.py
dlxapi/api/mappings_api.py
dlxapi/api/message_tokens_api.py
dlxapi/api/messages_api.py
dlxapi/api/notifications_api.py
dlxapi/api/plans_api.py
dlxapi/api/pods_api.py
dlxapi/api/portfolio_plan_users_api.py
dlxapi/api/portfolio_plans_api.py
dlxapi/api/portfolios_api.py
dlxapi/api/projects_api.py
dlxapi/api/properties_api.py
dlxapi/api/registration_api.py
dlxapi/api/reports_api.py
dlxapi/api/resource_pools_api.py
dlxapi/api/sources_api.py
dlxapi/api/spreadsheet_api.py
dlxapi/api/tags_api.py
dlxapi/api/user_api.py
dlxapi/api/users_api.py
dlxapi/models/__init__.py
dlxapi/models/access_token_generated_event.py
dlxapi/models/activities.py
dlxapi/models/activity.py
dlxapi/models/activity_type.py
dlxapi/models/add_user_request.py
dlxapi/models/add_users_request.py
dlxapi/models/added_to_portfolio_message_payload.py
dlxapi/models/added_to_portfolio_plan_message_payload.py
dlxapi/models/attachment.py
dlxapi/models/attachment_created_event.py
dlxapi/models/attachment_deleted_event.py
dlxapi/models/attachment_name_updated_event.py
dlxapi/models/attachment_updated_message_payload.py
dlxapi/models/attachments.py
dlxapi/models/attributes.py
dlxapi/models/authorization_code_generated_event.py
dlxapi/models/balance_field_detail.py
dlxapi/models/budget_allocation.py
dlxapi/models/budget_allocations.py
dlxapi/models/calculation_type.py
dlxapi/models/category_option.py
dlxapi/models/category_option_added_message_payload.py
dlxapi/models/category_option_created_event.py
dlxapi/models/category_option_deleted_event.py
dlxapi-1.0.0.dist-info/METADATA
dlxapi-1.0.0.dist-info/WHEEL
dlxapi-1.0.0.dist-info/top_level.txt
dlxapi-1.0.0.dist-info/RECORD
